parade_manage/__init__.py
parade_manage/base.py
parade_manage/constants.py
parade_manage/decorators.py
parade_manage/plugin.py
parade_manage/task.py
parade_manage/utils.py
parade_manage/common/__init__.py
parade_manage/common/dag.py
parade_manage/common/node.py
parade_manage-0.0.2.13.dist-info/LICENSE
parade_manage-0.0.2.13.dist-info/METADATA
parade_manage-0.0.2.13.dist-info/WHEEL
parade_manage-0.0.2.13.dist-info/top_level.txt
parade_manage-0.0.2.13.dist-info/RECORD
